<Properties StartupConfiguration="{BCAFE0B1-01CE-40EC-8B27-5B4E59BF3497}|Default">
  <MonoDevelop.Ide.ItemProperties.ButtonClick PreferredExecutionTarget="Test1" />
  <MonoDevelop.Ide.Workbench ActiveDocument="ButtonClick/ViewController.cs">
    <Files>
      <File FileName="ButtonClick/AppDelegate.cs" Line="23" Column="2" />
      <File FileName="ButtonClick/Info.plist" />
      <File FileName="ButtonClick/ViewController.cs" Line="1" Column="1" />
    </Files>
    <Pads>
      <Pad Id="ProjectPad">
        <State name="__root__">
          <Node name="ButtonClick" expanded="True">
            <Node name="ButtonClick" expanded="True">
              <Node name="ViewController.cs" expanded="True" selected="True" />
            </Node>
          </Node>
        </State>
      </Pad>
    </Pads>
  </MonoDevelop.Ide.Workbench>
  <MonoDevelop.Ide.DebuggingService.PinnedWatches />
  <MonoDevelop.Ide.Workspace ActiveConfiguration="Debug" />
  <MonoDevelop.Ide.DebuggingService.Breakpoints>
    <BreakpointStore />
  </MonoDevelop.Ide.DebuggingService.Breakpoints>
  <MultiItemStartupConfigurations />
</Properties>